hostprobe/__init__.py
hostprobe/_constants.py
hostprobe/_hostprobe.py
hostprobe/_version.py
hostprobe/exceptions.py
hostprobe/utils.py
hostprobe-1.0.0.dist-info/LICENSE
hostprobe-1.0.0.dist-info/METADATA
hostprobe-1.0.0.dist-info/WHEEL
hostprobe-1.0.0.dist-info/top_level.txt
hostprobe-1.0.0.dist-info/RECORD
