Metadata-Version: 2.1
Name: hostprobe
Version: 1.0.0
Summary: a cross-platform toolkit for probing networks in python
Author: malachi196
License: MIT License
Project-URL: Repository, https://github.com/malachi196/hostprobe/
Project-URL: Documentation, https://hostprobe.readthedocs.io/
Project-URL: Changelog, https://github.com/malachi196/hostprobe/blob/main/CHANGELOG.md
Classifier: License :: OSI Approved :: MIT License
Classifier: Development Status :: 4 - Beta
Classifier: Operating System :: MacOS
Classifier: Operating System :: Microsoft :: Windows
Classifier: Operating System :: Unix
Classifier: Operating System :: POSIX :: Linux
Requires-Python: >=3.6
License-File: LICENSE
Requires-Dist: psutil
Requires-Dist: colorama
